This file is a merged representation of the entire codebase, combined into a single document by Repomix.

<file_summary>
This section contains a summary of this file.

<purpose>
This file contains a packed representation of the entire repository's contents.
It is designed to be easily consumable by AI systems for analysis, code review,
or other automated processes.
</purpose>

<file_format>
The content is organized as follows:
1. This summary section
2. Repository information
3. Directory structure
4. Repository files (if enabled)
5. Multiple file entries, each consisting of:
  - File path as an attribute
  - Full contents of the file
</file_format>

<usage_guidelines>
- This file should be treated as read-only. Any changes should be made to the
  original repository files, not this packed version.
- When processing this file, use the file path to distinguish
  between different files in the repository.
- Be aware that this file may contain sensitive information. Handle it with
  the same level of security as you would the original repository.
</usage_guidelines>

<notes>
- Some files may have been excluded based on .gitignore rules and Repomix's configuration
- Binary files are not included in this packed representation. Please refer to the Repository Structure section for a complete list of file paths, including binary files
- Files matching patterns in .gitignore are excluded
- Files matching default ignore patterns are excluded
- Files are sorted by Git change count (files with more changes are at the bottom)
</notes>

</file_summary>

<directory_structure>
.github/
  workflows/
    deploy.yml
public/
  favicon.svg
src/
  assets/
    astro.svg
    background.svg
  components/
    Features.tsx
    Footer.astro
    Hero.tsx
    Navigation.astro
    Testimonials.tsx
    Welcome.astro
  data/
    business-data.json
  layouts/
    Layout.astro
  pages/
    contact.astro
    index.astro
    services.astro
    success.astro
  styles/
    global.css
.gitignore
astro.config.mjs
package.json
README.md
tailwind.config.mjs
tsconfig.json
</directory_structure>

<files>
This section contains the contents of the repository's files.

<file path="src/pages/contact.astro">
---
import Layout from '../layouts/Layout.astro';
import data from '../data/business-data.json';

// Define the success URL for the redirect
const baseUrl = import.meta.env.BASE_URL;
const successUrl = `https://yourusername.github.io${baseUrl}/success`;
---

<Layout title="Contact Us">
  <main class="py-24 px-6 max-w-7xl mx-auto">
    <div class="grid lg:grid-cols-2 gap-16">
      <div>
        <h1 class="text-4xl font-bold text-slate-900 leading-tight">
          Let's Build Something <br /> 
          <span class="text-brand-primary font-extrabold">Extraordinary.</span>
        </h1>
        <p class="mt-6 text-lg text-slate-600">
          Ready to launch your next {data.siteType} project? Fill out the form, and our team will get back to you within 24 hours.
        </p>

        <div class="mt-12 space-y-6">
          <div class="flex items-center gap-4">
            <div class="bg-slate-100 p-3 rounded-lg text-brand-primary">📧</div>
            <div>
              <p class="text-sm font-semibold text-slate-900">Email</p>
              <p class="text-slate-600">{data.contact.email}</p>
            </div>
          </div>
          <div class="flex items-center gap-4">
            <div class="bg-slate-100 p-3 rounded-lg text-brand-primary">📞</div>
            <div>
              <p class="text-sm font-semibold text-slate-900">Phone</p>
              <p class="text-slate-600">{data.contact.phone}</p>
            </div>
          </div>
        </div>
      </div>

      <div class="bg-white p-8 border border-slate-200 rounded-2xl shadow-sm">
        <form action="https://formspree.io/f/YOUR_ID" method="POST" class="space-y-6">
          
          <input type="hidden" name="_next" value={successUrl} />
          <input type="hidden" name="_subject" value={`New Lead from ${data.businessName}`} />

          <div>
            <label for="name" class="block text-sm font-medium text-slate-700">Full Name</label>
            <input type="text" name="name" id="name" required class="mt-1 block w-full rounded-md border-slate-300 shadow-sm focus:border-brand-primary focus:ring-brand-primary text-slate-900 p-3 border" />
          </div>
          <div>
            <label for="email" class="block text-sm font-medium text-slate-700">Email Address</label>
            <input type="email" name="email" id="email" required class="mt-1 block w-full rounded-md border-slate-300 shadow-sm focus:border-brand-primary focus:ring-brand-primary text-slate-900 p-3 border" />
          </div>
          <div>
            <label for="message" class="block text-sm font-medium text-slate-700">Message</label>
            <textarea id="message" name="message" rows="4" required class="mt-1 block w-full rounded-md border-slate-300 shadow-sm focus:border-brand-primary focus:ring-brand-primary text-slate-900 p-3 border"></textarea>
          </div>
          
          <button type="submit" class="w-full bg-brand-primary text-white font-semibold py-3 px-6 rounded-lg hover:bg-brand-hover transition-all shadow-md active:scale-95">
            Send Message
          </button>
        </form>
      </div>
    </div>
  </main>
</Layout>
</file>

<file path="src/pages/success.astro">
---
import Layout from '../layouts/Layout.astro';
import data from '../data/business-data.json';
const baseUrl = import.meta.env.BASE_URL;
---

<Layout title="Message Sent">
  <main class="py-32 px-6 text-center max-w-7xl mx-auto">
    <div class="inline-flex items-center justify-center w-20 h-20 bg-green-100 text-green-600 rounded-full mb-8">
      <svg xmlns="http://www.w3.org/2000/svg" class="h-10 w-10" fill="none" viewBox="0 0 24 24" stroke="currentColor">
        <path stroke-linecap="round" stroke-linejoin="round" stroke-width="3" d="M5 13l4 4L19 7" />
      </svg>
    </div>
    
    <h1 class="text-4xl font-bold text-slate-900 leading-tight">
      Thank You!
    </h1>
    <p class="mt-4 text-lg text-slate-600 max-w-md mx-auto">
      Your message has been sent to the {data.businessName} team. We'll get back to you shortly.
    </p>

    <div class="mt-10">
      <a 
        href={baseUrl} 
        class="inline-block bg-brand-primary text-white font-semibold py-3 px-8 rounded-full hover:bg-brand-hover transition-all"
      >
        Back to Home
      </a>
    </div>
  </main>
</Layout>
</file>

<file path=".github/workflows/deploy.yml">
name: Deploy to GitHub Pages

on:
  push:
    branches: [main]
  workflow_dispatch:

permissions:
  contents: read
  pages: write
  id-token: write

jobs:
  build:
    runs-on: ubuntu-latest
    steps:
      - name: Checkout
        uses: actions/checkout@v4

      - name: Setup Node
        uses: actions/setup-node@v4
        with:
          node-version: 20
          cache: 'npm'

      - name: Install dependencies
        run: npm install

      - name: Build Astro
        run: npm run build

      - name: Upload artifact
        uses: actions/upload-pages-artifact@v3
        with:
          path: ./dist

  deploy:
    needs: build
    runs-on: ubuntu-latest
    environment:
      name: github-pages
      url: ${{ steps.deployment.outputs.page_url }}
    steps:
      - name: Deploy to GitHub Pages
        id: deployment
        uses: actions/deploy-pages@v4
</file>

<file path="public/favicon.svg">
<svg xmlns="http://www.w3.org/2000/svg" fill="none" viewBox="0 0 128 128">
    <path d="M50.4 78.5a75.1 75.1 0 0 0-28.5 6.9l24.2-65.7c.7-2 1.9-3.2 3.4-3.2h29c1.5 0 2.7 1.2 3.4 3.2l24.2 65.7s-11.6-7-28.5-7L67 45.5c-.4-1.7-1.6-2.8-2.9-2.8-1.3 0-2.5 1.1-2.9 2.7L50.4 78.5Zm-1.1 28.2Zm-4.2-20.2c-2 6.6-.6 15.8 4.2 20.2a17.5 17.5 0 0 1 .2-.7 5.5 5.5 0 0 1 5.7-4.5c2.8.1 4.3 1.5 4.7 4.7.2 1.1.2 2.3.2 3.5v.4c0 2.7.7 5.2 2.2 7.4a13 13 0 0 0 5.7 4.9v-.3l-.2-.3c-1.8-5.6-.5-9.5 4.4-12.8l1.5-1a73 73 0 0 0 3.2-2.2 16 16 0 0 0 6.8-11.4c.3-2 .1-4-.6-6l-.8.6-1.6 1a37 37 0 0 1-22.4 2.7c-5-.7-9.7-2-13.2-6.2Z" />
    <style>
        path { fill: #000; }
        @media (prefers-color-scheme: dark) {
            path { fill: #FFF; }
        }
    </style>
</svg>
</file>

<file path="src/assets/astro.svg">
<svg xmlns="http://www.w3.org/2000/svg" fill="none" width="115" height="48"><path fill="#17191E" d="M7.77 36.35C6.4 35.11 6 32.51 6.57 30.62c.99 1.2 2.35 1.57 3.75 1.78 2.18.33 4.31.2 6.33-.78.23-.12.44-.27.7-.42.18.55.23 1.1.17 1.67a4.56 4.56 0 0 1-1.94 3.23c-.43.32-.9.61-1.34.91-1.38.94-1.76 2.03-1.24 3.62l.05.17a3.63 3.63 0 0 1-1.6-1.38 3.87 3.87 0 0 1-.63-2.1c0-.37 0-.74-.05-1.1-.13-.9-.55-1.3-1.33-1.32a1.56 1.56 0 0 0-1.63 1.26c0 .06-.03.12-.05.2Z"/><path fill="url(#a)" d="M7.77 36.35C6.4 35.11 6 32.51 6.57 30.62c.99 1.2 2.35 1.57 3.75 1.78 2.18.33 4.31.2 6.33-.78.23-.12.44-.27.7-.42.18.55.23 1.1.17 1.67a4.56 4.56 0 0 1-1.94 3.23c-.43.32-.9.61-1.34.91-1.38.94-1.76 2.03-1.24 3.62l.05.17a3.63 3.63 0 0 1-1.6-1.38 3.87 3.87 0 0 1-.63-2.1c0-.37 0-.74-.05-1.1-.13-.9-.55-1.3-1.33-1.32a1.56 1.56 0 0 0-1.63 1.26c0 .06-.03.12-.05.2Z"/><path fill="#17191E" d="M.02 30.31s4.02-1.95 8.05-1.95l3.04-9.4c.11-.45.44-.76.82-.76.37 0 .7.31.82.76l3.04 9.4c4.77 0 8.05 1.95 8.05 1.95L17 11.71c-.2-.56-.53-.91-.98-.91H7.83c-.44 0-.76.35-.97.9L.02 30.31Zm42.37-5.97c0 1.64-2.05 2.62-4.88 2.62-1.85 0-2.5-.45-2.5-1.41 0-1 .8-1.49 2.65-1.49 1.67 0 3.09.03 4.73.23v.05Zm.03-2.04a21.37 21.37 0 0 0-4.37-.36c-5.32 0-7.82 1.25-7.82 4.18 0 3.04 1.71 4.2 5.68 4.2 3.35 0 5.63-.84 6.46-2.92h.14c-.03.5-.05 1-.05 1.4 0 1.07.18 1.16 1.06 1.16h4.15a16.9 16.9 0 0 1-.36-4c0-1.67.06-2.93.06-4.62 0-3.45-2.07-5.64-8.56-5.64-2.8 0-5.9.48-8.26 1.19.22.93.54 2.83.7 4.06 2.04-.96 4.95-1.37 7.2-1.37 3.11 0 3.97.71 3.97 2.15v.57Zm11.37 3c-.56.07-1.33.07-2.12.07-.83 0-1.6-.03-2.12-.1l-.02.58c0 2.85 1.87 4.52 8.45 4.52 6.2 0 8.2-1.64 8.2-4.55 0-2.74-1.33-4.09-7.2-4.39-4.58-.2-4.99-.7-4.99-1.28 0-.66.59-1 3.65-1 3.18 0 4.03.43 4.03 1.35v.2a46.13 46.13 0 0 1 4.24.03l.02-.55c0-3.36-2.8-4.46-8.2-4.46-6.08 0-8.13 1.49-8.13 4.39 0 2.6 1.64 4.23 7.48 4.48 4.3.14 4.77.62 4.77 1.28 0 .7-.7 1.03-3.71 1.03-3.47 0-4.35-.48-4.35-1.47v-.13Zm19.82-12.05a17.5 17.5 0 0 1-6.24 3.48c.03.84.03 2.4.03 3.24l1.5.02c-.02 1.63-.04 3.6-.04 4.9 0 3.04 1.6 5.32 6.58 5.32 2.1 0 3.5-.23 5.23-.6a43.77 43.77 0 0 1-.46-4.13c-1.03.34-2.34.53-3.78.53-2 0-2.82-.55-2.82-2.13 0-1.37 0-2.65.03-3.84 2.57.02 5.13.07 6.64.11-.02-1.18.03-2.9.1-4.04-2.2.04-4.65.07-6.68.07l.07-2.93h-.16Zm13.46 6.04a767.33 767.33 0 0 1 .07-3.18H82.6c.07 1.96.07 3.98.07 6.92 0 2.95-.03 4.99-.07 6.93h5.18c-.09-1.37-.11-3.68-.11-5.65 0-3.1 1.26-4 4.12-4 1.33 0 2.28.16 3.1.46.03-1.16.26-3.43.4-4.43-.86-.25-1.81-.41-2.96-.41-2.46-.03-4.26.98-5.1 3.38l-.17-.02Zm22.55 3.65c0 2.5-1.8 3.66-4.64 3.66-2.81 0-4.61-1.1-4.61-3.66s1.82-3.52 4.61-3.52c2.82 0 4.64 1.03 4.64 3.52Zm4.71-.11c0-4.96-3.87-7.18-9.35-7.18-5.5 0-9.23 2.22-9.23 7.18 0 4.94 3.49 7.59 9.21 7.59 5.77 0 9.37-2.65 9.37-7.6Z"/><defs><linearGradient id="a" x1="6.33" x2="19.43" y1="40.8" y2="34.6" gradientUnits="userSpaceOnUse"><stop stop-color="#D83333"/><stop offset="1" stop-color="#F041FF"/></linearGradient></defs></svg>
</file>

<file path="src/assets/background.svg">
<svg xmlns="http://www.w3.org/2000/svg" width="1440" height="1024" fill="none"><path fill="url(#a)" fill-rule="evenodd" d="M-217.58 475.75c91.82-72.02 225.52-29.38 341.2-44.74C240 415.56 372.33 315.14 466.77 384.9c102.9 76.02 44.74 246.76 90.31 366.31 29.83 78.24 90.48 136.14 129.48 210.23 57.92 109.99 169.67 208.23 155.9 331.77-13.52 121.26-103.42 264.33-224.23 281.37-141.96 20.03-232.72-220.96-374.06-196.99-151.7 25.73-172.68 330.24-325.85 315.72-128.6-12.2-110.9-230.73-128.15-358.76-12.16-90.14 65.87-176.25 44.1-264.57-26.42-107.2-167.12-163.46-176.72-273.45-10.15-116.29 33.01-248.75 124.87-320.79Z" clip-rule="evenodd" style="opacity:.154"/><path fill="url(#b)" fill-rule="evenodd" d="M1103.43 115.43c146.42-19.45 275.33-155.84 413.5-103.59 188.09 71.13 409 212.64 407.06 413.88-1.94 201.25-259.28 278.6-414.96 405.96-130 106.35-240.24 294.39-405.6 265.3-163.7-28.8-161.93-274.12-284.34-386.66-134.95-124.06-436-101.46-445.82-284.6-9.68-180.38 247.41-246.3 413.54-316.9 101.01-42.93 207.83 21.06 316.62 6.61Z" clip-rule="evenodd" style="opacity:.154"/><defs><linearGradient id="b" x1="373" x2="1995.44" y1="1100" y2="118.03" gradientUnits="userSpaceOnUse"><stop stop-color="#D83333"/><stop offset="1" stop-color="#F041FF"/></linearGradient><linearGradient id="a" x1="107.37" x2="1130.66" y1="1993.35" y2="1026.31" gradientUnits="userSpaceOnUse"><stop stop-color="#3245FF"/><stop offset="1" stop-color="#BC52EE"/></linearGradient></defs></svg>
</file>

<file path="src/components/Features.tsx">
import React from 'react';
import data from '../data/business-data.json';

const featureContent = {
  service: [
    { title: "Expert Consulting", desc: "Professional advice tailored to your growth." },
    { title: "24/7 Support", desc: "We are always here when your business needs us." },
    { title: "Data Analytics", desc: "Deep insights into your service performance." }
  ],
  shop: [
    { title: "Secure Payments", desc: "Fully encrypted checkout for your customers." },
    { title: "Fast Shipping", desc: "Logistics optimized for global delivery." },
    { title: "Inventory Sync", desc: "Real-time updates across all your platforms." }
  ],
  portfolio: [
    { title: "HD Galleries", desc: "Showcase your work in stunning high definition." },
    { title: "Case Studies", desc: "Detailed breakdowns of your creative process." },
    { title: "Client Testimonials", desc: "Social proof built directly into your work." }
  ]
};

export default function Features() {
  const type = data.siteType as keyof typeof featureContent;
  const items = featureContent[type] || featureContent.service;

  return (
    <section className="py-24 bg-slate-50">
      <div className="mx-auto max-w-7xl px-6 lg:px-8">
        <div className="grid grid-cols-1 gap-12 sm:grid-cols-2 lg:grid-cols-3">
          {items.map((item, index) => (
            <div key={index} className="flex flex-col p-8 bg-white rounded-2xl border border-slate-200 shadow-sm hover:shadow-md transition-shadow">
              {/* Dynamic Branding Applied Below: bg-brand-primary */}
              <div className="h-10 w-10 rounded-lg bg-brand-primary mb-6 flex items-center justify-center">
                <div className="h-5 w-5 border-2 border-white rounded-full" />
              </div>
              <h3 className="text-xl font-bold text-slate-900">{item.title}</h3>
              <p className="mt-4 text-slate-600 leading-relaxed">{item.desc}</p>
            </div>
          ))}
        </div>
      </div>
    </section>
  );
}
</file>

<file path="src/components/Hero.tsx">
import React from 'react';
import data from '../data/business-data.json';

export default function Hero() {
  const ctaText = data.cta[data.siteType as keyof typeof data.cta];
  const baseUrl = "/agency-v3"; // Match your config

  return (
    <section className="relative overflow-hidden bg-white py-24 sm:py-32">
      <div className="mx-auto max-w-7xl px-6 lg:px-8">
        <div className="mx-auto max-w-2xl text-center">
          <h1 className="text-4xl font-bold tracking-tight text-gray-900 sm:text-6xl">
            Modern Solutions for <span className="text-brand-primary">{data.businessName}</span>
          </h1>
          <p className="mt-6 text-lg leading-8 text-gray-600">
            We build high-performance, AI-ready static sites tailored for {data.siteType} businesses.
          </p>
          <div className="mt-10 flex items-center justify-center gap-x-6">
            <a
              href={`${baseUrl}/contact`}
              className="rounded-full bg-brand-primary px-8 py-3 text-sm font-semibold text-white shadow-sm hover:bg-brand-hover transition-all"
            >
              {ctaText}
            </a>
          </div>
        </div>
      </div>
    </section>
  );
}
</file>

<file path="src/components/Testimonials.tsx">
import React from 'react';
import data from '../data/business-data.json';

export default function Testimonials() {
  return (
    <section className="py-24 bg-white">
      <div className="mx-auto max-w-7xl px-6 lg:px-8 text-center">
        <h2 className="text-3xl font-bold tracking-tight text-gray-900 sm:text-4xl">
          Trusted by Industry Leaders
        </h2>
        <p className="mt-4 text-lg leading-8 text-gray-600">
          See why businesses choose {data.businessName} for their digital presence.
        </p>
        <div className="mt-16 grid grid-cols-1 gap-8 sm:grid-cols-2 lg:mx-0 lg:max-w-none">
          {data.testimonials.map((t, index) => (
            <div key={index} className="flex flex-col items-start gap-y-6 rounded-2xl bg-slate-50 p-8 border border-slate-100">
              <p className="text-lg italic text-slate-700 leading-relaxed">"{t.quote}"</p>
              <div className="flex items-center gap-x-4">
                <img src={t.image} alt={t.name} className="h-12 w-12 rounded-full bg-slate-200" />
                <div className="text-left">
                  <div className="font-semibold text-slate-900">{t.name}</div>
                  <div className="text-sm text-slate-500">{t.role}</div>
                </div>
              </div>
            </div>
          ))}
        </div>
      </div>
    </section>
  );
}
</file>

<file path="src/components/Welcome.astro">
---
import astroLogo from '../assets/astro.svg';
import background from '../assets/background.svg';
---

<div id="container">
	<img id="background" src={background.src} alt="" fetchpriority="high" />
	<main>
		<section id="hero">
			<a href="https://astro.build"
				><img src={astroLogo.src} width="115" height="48" alt="Astro Homepage" /></a
			>
			<h1>
				To get started, open the <code><pre>src/pages</pre></code> directory in your project.
			</h1>
			<section id="links">
				<a class="button" href="https://docs.astro.build">Read our docs</a>
				<a href="https://astro.build/chat"
					>Join our Discord <svg xmlns="http://www.w3.org/2000/svg" viewBox="0 0 127.14 96.36"
						><path
							fill="currentColor"
							d="M107.7 8.07A105.15 105.15 0 0 0 81.47 0a72.06 72.06 0 0 0-3.36 6.83 97.68 97.68 0 0 0-29.11 0A72.37 72.37 0 0 0 45.64 0a105.89 105.89 0 0 0-26.25 8.09C2.79 32.65-1.71 56.6.54 80.21a105.73 105.73 0 0 0 32.17 16.15 77.7 77.7 0 0 0 6.89-11.11 68.42 68.42 0 0 1-10.85-5.18c.91-.66 1.8-1.34 2.66-2a75.57 75.57 0 0 0 64.32 0c.87.71 1.76 1.39 2.66 2a68.68 68.68 0 0 1-10.87 5.19 77 77 0 0 0 6.89 11.1 105.25 105.25 0 0 0 32.19-16.14c2.64-27.38-4.51-51.11-18.9-72.15ZM42.45 65.69C36.18 65.69 31 60 31 53s5-12.74 11.43-12.74S54 46 53.89 53s-5.05 12.69-11.44 12.69Zm42.24 0C78.41 65.69 73.25 60 73.25 53s5-12.74 11.44-12.74S96.23 46 96.12 53s-5.04 12.69-11.43 12.69Z"
						></path></svg
					>
				</a>
			</section>
		</section>
	</main>

	<a href="https://astro.build/blog/astro-5/" id="news" class="box">
		<svg width="32" height="32" fill="none" xmlns="http://www.w3.org/2000/svg"
			><path
				d="M24.667 12c1.333 1.414 2 3.192 2 5.334 0 4.62-4.934 5.7-7.334 12C18.444 28.567 18 27.456 18 26c0-4.642 6.667-7.053 6.667-14Zm-5.334-5.333c1.6 1.65 2.4 3.43 2.4 5.333 0 6.602-8.06 7.59-6.4 17.334C13.111 27.787 12 25.564 12 22.666c0-4.434 7.333-8 7.333-16Zm-6-5.333C15.111 3.555 16 5.556 16 7.333c0 8.333-11.333 10.962-5.333 22-3.488-.774-6-4-6-8 0-8.667 8.666-10 8.666-20Z"
				fill="#111827"></path></svg
		>
		<h2>What's New in Astro 5.0?</h2>
		<p>
			From content layers to server islands, click to learn more about the new features and
			improvements in Astro 5.0
		</p>
	</a>
</div>

<style>
	#background {
		position: fixed;
		top: 0;
		left: 0;
		width: 100%;
		height: 100%;
		z-index: -1;
		filter: blur(100px);
	}

	#container {
		font-family: Inter, Roboto, 'Helvetica Neue', 'Arial Nova', 'Nimbus Sans', Arial, sans-serif;
		height: 100%;
	}

	main {
		height: 100%;
		display: flex;
		justify-content: center;
	}

	#hero {
		display: flex;
		align-items: start;
		flex-direction: column;
		justify-content: center;
		padding: 16px;
	}

	h1 {
		font-size: 22px;
		margin-top: 0.25em;
	}

	#links {
		display: flex;
		gap: 16px;
	}

	#links a {
		display: flex;
		align-items: center;
		padding: 10px 12px;
		color: #111827;
		text-decoration: none;
		transition: color 0.2s;
	}

	#links a:hover {
		color: rgb(78, 80, 86);
	}

	#links a svg {
		height: 1em;
		margin-left: 8px;
	}

	#links a.button {
		color: white;
		background: linear-gradient(83.21deg, #3245ff 0%, #bc52ee 100%);
		box-shadow:
			inset 0 0 0 1px rgba(255, 255, 255, 0.12),
			inset 0 -2px 0 rgba(0, 0, 0, 0.24);
		border-radius: 10px;
	}

	#links a.button:hover {
		color: rgb(230, 230, 230);
		box-shadow: none;
	}

	pre {
		font-family:
			ui-monospace, 'Cascadia Code', 'Source Code Pro', Menlo, Consolas, 'DejaVu Sans Mono',
			monospace;
		font-weight: normal;
		background: linear-gradient(14deg, #d83333 0%, #f041ff 100%);
		-webkit-background-clip: text;
		-webkit-text-fill-color: transparent;
		background-clip: text;
		margin: 0;
	}

	h2 {
		margin: 0 0 1em;
		font-weight: normal;
		color: #111827;
		font-size: 20px;
	}

	p {
		color: #4b5563;
		font-size: 16px;
		line-height: 24px;
		letter-spacing: -0.006em;
		margin: 0;
	}

	code {
		display: inline-block;
		background:
			linear-gradient(66.77deg, #f3cddd 0%, #f5cee7 100%) padding-box,
			linear-gradient(155deg, #d83333 0%, #f041ff 18%, #f5cee7 45%) border-box;
		border-radius: 8px;
		border: 1px solid transparent;
		padding: 6px 8px;
	}

	.box {
		padding: 16px;
		background: rgba(255, 255, 255, 1);
		border-radius: 16px;
		border: 1px solid white;
	}

	#news {
		position: absolute;
		bottom: 16px;
		right: 16px;
		max-width: 300px;
		text-decoration: none;
		transition: background 0.2s;
		backdrop-filter: blur(50px);
	}

	#news:hover {
		background: rgba(255, 255, 255, 0.55);
	}

	@media screen and (max-height: 368px) {
		#news {
			display: none;
		}
	}

	@media screen and (max-width: 768px) {
		#container {
			display: flex;
			flex-direction: column;
		}

		#hero {
			display: block;
			padding-top: 10%;
		}

		#links {
			flex-wrap: wrap;
		}

		#links a.button {
			padding: 14px 18px;
		}

		#news {
			right: 16px;
			left: 16px;
			bottom: 2.5rem;
			max-width: 100%;
		}

		h1 {
			line-height: 1.5;
		}
	}
</style>
</file>

<file path="src/pages/services.astro">
---
import Layout from '../layouts/Layout.astro';
import data from '../data/business-data.json';
---

<Layout title="Our Services">
	<main class="py-24 px-6 max-w-7xl mx-auto">
		<h1 class="text-4xl font-bold text-slate-900">Our Services</h1>
		<p class="mt-4 text-lg text-slate-600">
            Specialized solutions for our {data.siteType} clients.
        </p>
	</main>
</Layout>
</file>

<file path="src/styles/global.css">
@tailwind base;
@tailwind components;
@tailwind utilities;
</file>

<file path=".gitignore">
# build output
dist/

# generated types
.astro/

# dependencies
node_modules/

# logs
npm-debug.log*
yarn-debug.log*
yarn-error.log*
pnpm-debug.log*

# environment variables
.env
.env.production

# macOS-specific files
.DS_Store

# jetbrains setting folder
.idea/
</file>

<file path="README.md">
# Astro Starter Kit: Basics

```sh
npm create astro@latest -- --template basics
```

> 🧑‍🚀 **Seasoned astronaut?** Delete this file. Have fun!

## 🚀 Project Structure

Inside of your Astro project, you'll see the following folders and files:

```text
/
├── public/
│   └── favicon.svg
├── src
│   ├── assets
│   │   └── astro.svg
│   ├── components
│   │   └── Welcome.astro
│   ├── layouts
│   │   └── Layout.astro
│   └── pages
│       └── index.astro
└── package.json
```

To learn more about the folder structure of an Astro project, refer to [our guide on project structure](https://docs.astro.build/en/basics/project-structure/).

## 🧞 Commands

All commands are run from the root of the project, from a terminal:

| Command                   | Action                                           |
| :------------------------ | :----------------------------------------------- |
| `npm install`             | Installs dependencies                            |
| `npm run dev`             | Starts local dev server at `localhost:4321`      |
| `npm run build`           | Build your production site to `./dist/`          |
| `npm run preview`         | Preview your build locally, before deploying     |
| `npm run astro ...`       | Run CLI commands like `astro add`, `astro check` |
| `npm run astro -- --help` | Get help using the Astro CLI                     |

## 👀 Want to learn more?

Feel free to check [our documentation](https://docs.astro.build) or jump into our [Discord server](https://astro.build/chat).
</file>

<file path="tailwind.config.mjs">
/** @type {import('tailwindcss').Config} */
export default {
    content: ['./src/**/*.{astro,html,js,jsx,md,mdx,svelte,ts,tsx,vue}'],
    theme: {
      extend: {
        colors: {
          brand: {
            primary: 'var(--brand-primary)',
            hover: 'var(--brand-hover)',
            accent: 'var(--brand-accent)',
          }
        }
      },
    },
    plugins: [],
  }
</file>

<file path="tsconfig.json">
{
  "extends": "astro/tsconfigs/strict",
  "include": [".astro/types.d.ts", "**/*"],
  "exclude": ["dist"]
}
</file>

<file path="src/components/Footer.astro">
---
import data from '../data/business-data.json';
const year = new Date().getFullYear();
const baseUrl = import.meta.env.BASE_URL;
---

<footer class="bg-white border-t border-slate-200 pt-16 pb-8">
  <div class="mx-auto max-w-7xl px-6 lg:px-8">
    <div class="xl:grid xl:grid-cols-3 xl:gap-8">
      <div class="space-y-8">
        <span class="text-2xl font-bold tracking-tight text-slate-900">{data.businessName}</span>
        <p class="text-sm leading-6 text-slate-600 max-w-xs">
          Building high-performance, AI-ready {data.siteType} sites in record time.
        </p>
        <div class="flex gap-x-6">
          {data.socials.map((social) => (
            <a href={social.url} target="_blank" rel="noopener noreferrer" class="text-slate-400 hover:text-slate-600 text-sm transition-colors">
              {social.platform}
            </a>
          ))}
        </div>
      </div>

      <div class="mt-16 grid grid-cols-2 gap-8 xl:col-span-2 xl:mt-0">
        <div>
          <h3 class="text-sm font-semibold leading-6 text-slate-900">Navigation</h3>
          <ul role="list" class="mt-6 space-y-4">
            {data.navigation.map((item) => (
              <li>
                <a 
                  href={`${baseUrl}/${item.href}`} 
                  class="text-sm leading-6 text-slate-600 hover:text-slate-900 transition-colors"
                >
                  {item.label}
                </a>
              </li>
            ))}
          </ul>
        </div>
        <div>
          <h3 class="text-sm font-semibold leading-6 text-slate-900">Contact</h3>
          <ul role="list" class="mt-6 space-y-4 text-sm leading-6 text-slate-600">
            <li>{data.contact.email}</li>
            <li>{data.contact.phone}</li>
            <li>{data.contact.address}</li>
          </ul>
        </div>
      </div>
    </div>
    
    <div class="mt-16 border-t border-slate-900/5 pt-8 sm:mt-20 lg:mt-24">
      <p class="text-xs leading-5 text-slate-500">
        &copy; {year} {data.businessName}. All rights reserved.
      </p>
    </div>
  </div>
</footer>
</file>

<file path="src/components/Navigation.astro">
---
import data from '../data/business-data.json';
const baseUrl = import.meta.env.BASE_URL;
const activeCta = data.cta[data.siteType as keyof typeof data.cta];
---

<nav class="p-6 bg-white border-b border-gray-100">
  <div class="flex items-center justify-between">
    <a href={baseUrl} class="text-xl font-bold text-slate-900">
      {data.businessName}
    </a>

    <div class="hidden md:flex gap-6">
      {data.navigation.map((item) => (
        <a 
          href={`${baseUrl}/${item.href}`} 
          class="text-gray-600 hover:text-black transition-colors"
        >
          {item.label}
        </a>
      ))}
    </div>

    <div class="flex items-center gap-4">
      <a 
        href={`${baseUrl}/contact`} 
        class="hidden sm:block px-6 py-2 bg-brand-primary text-white rounded-full text-sm font-medium hover:bg-brand-hover transition-all"
      >
        {activeCta}
      </a>
      
      <button id="menu-toggle" class="md:hidden p-2 text-gray-600 focus:outline-none">
        <svg xmlns="http://www.w3.org/2000/svg" class="h-6 w-6" fill="none" viewBox="0 0 24 24" stroke="currentColor">
          <path stroke-linecap="round" stroke-linejoin="round" stroke-width="2" d="M4 6h16M4 12h16m-7 6h7" />
        </svg>
      </button>
    </div>
  </div>

  <div id="mobile-menu" class="hidden md:hidden mt-4 space-y-4 pb-4">
    {data.navigation.map((item) => (
      <a 
        href={`${baseUrl}/${item.href}`} 
        class="block text-gray-600 hover:text-black border-b border-gray-50 pb-2"
      >
        {item.label}
      </a>
    ))}
    <a 
      href={`${baseUrl}/contact`} 
      class="block text-brand-primary font-bold"
    >
      {activeCta}
    </a>
  </div>
</nav>

<script>
  const btn = document.getElementById('menu-toggle');
  const menu = document.getElementById('mobile-menu');

  btn?.addEventListener('click', () => {
    menu?.classList.toggle('hidden');
  });
</script>
</file>

<file path="src/layouts/Layout.astro">
---
import Navigation from '../components/Navigation.astro';
import Footer from '../components/Footer.astro';
import '../styles/global.css';
import data from '../data/business-data.json';

const { title } = Astro.props;

// Pull the theme object from JSON, or provide defaults as a fallback
const theme = data.theme || {
  primary: "#2563eb",
  primaryHover: "#1d4ed8",
  accent: "#eff6ff"
};
---

<!doctype html>
<html lang="en">
	<head>
		<meta charset="UTF-8" />
		<meta name="viewport" content="width=device-width" />
		<link rel="icon" type="image/svg+xml" href={`${import.meta.env.BASE_URL}/favicon.svg`} />
		<title>{title} | {data.businessName}</title>

		<style define:vars={{ 
			'brand-primary': theme.primary, 
			'brand-hover': theme.primaryHover,
			'brand-accent': theme.accent 
		}}>
			/* These variables are now available globally in your project */
			:root {
				--brand-color: var(--brand-primary);
			}
		</style>
	</head>
	<body class="bg-white">
		<Navigation />
		<slot /> 
		<Footer />
	</body>
</html>
</file>

<file path="astro.config.mjs">
import { defineConfig } from 'astro/config';
import tailwind from '@astrojs/tailwind';
import react from '@astrojs/react';

export default defineConfig({
  site: 'https://username.github.io',
  base: '/agency-v3',
  integrations: [
    tailwind({ applyBaseStyles: false }), 
    react()
  ],
  output: 'static',
});
</file>

<file path="package.json">
{
  "name": "agency-v3",
  "type": "module",
  "version": "0.0.1",
  "scripts": {
    "dev": "astro dev",
    "build": "astro build",
    "preview": "astro preview",
    "astro": "astro"
  },
  "dependencies": {
    "@astrojs/react": "^4.4.2",
    "@astrojs/tailwind": "^5.1.5",
    "astro": "^5.16.6",
    "react": "^19.2.3",
    "react-dom": "^19.2.3",
    "tailwindcss": "^3.4.19"
  }
}
</file>

<file path="src/data/business-data.json">
{
    "businessName": "Agency Zero",
    "siteType": "service",
    "navigation": [
     { "label": "Home", "href": "" },
     { "label": "Services", "href": "services" },
     { "label": "Contact", "href": "contact" }
    ],
    "cta": { 
      "service": "Book Now", 
      "shop": "Buy Now",
      "portfolio": "View Work"
    },
    "contact": {
      "email": "hello@agencyzero.com",
      "phone": "+1 (555) 000-0000",
      "address": "123 Tech Lane, Digital City"
    },
    "socials": [
      { "platform": "Twitter", "url": "https://twitter.com" },
      { "platform": "LinkedIn", "url": "https://linkedin.com" },
      { "platform": "GitHub", "url": "https://github.com" }
    ],
    "testimonials": [
      {
        "name": "Alex Rivera",
        "role": "CEO, TechFlow",
        "quote": "This team delivered our site in record time. The performance is unmatched.",
        "image": "https://i.pravatar.cc/150?u=alex"
      },
      {
        "name": "Sarah Chen",
        "role": "Founder, Bloom",
        "quote": "The AI-driven approach they used for our shop simplified everything.",
        "image": "https://i.pravatar.cc/150?u=sarah"
      }
    ],
    "theme": {
       "primary": "#2563eb", 
       "primaryHover": "#1d4ed8",
       "accent": "#eff6ff"
    }
  }
</file>

<file path="src/pages/index.astro">
---
import Layout from '../layouts/Layout.astro';
import Hero from '../components/Hero';
import Features from '../components/Features';
import Testimonials from '../components/Testimonials';
---

<Layout title="Home">
	<main>
		<Hero />
		<Features />
		<Testimonials />
	</main>
</Layout>
</file>

</files>
